{
  "gf_path": "C:\\MyCode\\Grammatical_Framework\\AlbanianSQI\\GF\\lib\\src\\albanian\\MorphoSqi.gf",
  "parts_dir": "C:\\MyCode\\Grammatical_Framework\\AlbanianSQI\\GF\\lib\\src\\albanian\\MorphoSqi_parts",
  "header_marker_regex": "^\\s*oper\\s*$",
  "section_start_regex": "^\\s*(mk[ANV])(\\d+)\\s*:",
  "header_end": 4,
  "footer_start": 42621,
  "naming": "structured",
  "bucket_size": 10,
  "part_files": [
    "10_Noun_mkN001-010.gfpart",
    "10_Noun_mkN011-020.gfpart",
    "10_Noun_mkN021-030.gfpart",
    "10_Noun_mkN031-040.gfpart",
    "10_Noun_mkN041-050.gfpart",
    "10_Noun_mkN051-060.gfpart",
    "10_Noun_mkN061-070.gfpart",
    "10_Noun_mkN071-080.gfpart",
    "10_Noun_mkN081-090.gfpart",
    "10_Noun_mkN091-100.gfpart",
    "10_Noun_mkN101-110.gfpart",
    "10_Noun_mkN111-120.gfpart",
    "10_Noun_mkN121-130.gfpart",
    "10_Noun_mkN131-140.gfpart",
    "10_Noun_mkN141-150.gfpart",
    "10_Noun_mkN151-160.gfpart",
    "10_Noun_mkN161-170.gfpart",
    "10_Noun_mkN171-180.gfpart",
    "10_Noun_mkN181-190.gfpart",
    "10_Noun_mkN191-200.gfpart",
    "10_Noun_mkN201-210.gfpart",
    "10_Noun_mkN211-220.gfpart",
    "10_Noun_mkN221-230.gfpart",
    "10_Noun_mkN231-240.gfpart",
    "10_Noun_mkN241-250.gfpart",
    "10_Noun_mkN251-260.gfpart",
    "10_Noun_mkN261-270.gfpart",
    "10_Noun_mkN271-280.gfpart",
    "10_Noun_mkN281-290.gfpart",
    "10_Noun_mkN291-300.gfpart",
    "10_Noun_mkN301-310.gfpart",
    "10_Noun_mkN311-320.gfpart",
    "10_Noun_mkN321-330.gfpart",
    "10_Noun_mkN331-340.gfpart",
    "10_Noun_mkN341-350.gfpart",
    "10_Noun_mkN351-360.gfpart",
    "10_Noun_mkN361-370.gfpart",
    "10_Noun_mkN371-380.gfpart",
    "10_Noun_mkN381-390.gfpart",
    "10_Noun_mkN391-400.gfpart",
    "10_Noun_mkN401-410.gfpart",
    "10_Noun_mkN411-420.gfpart",
    "10_Noun_mkN421-430.gfpart",
    "10_Noun_mkN431-440.gfpart",
    "10_Noun_mkN441-450.gfpart",
    "10_Noun_mkN451-460.gfpart",
    "10_Noun_mkN461-470.gfpart",
    "10_Noun_mkN471-480.gfpart",
    "10_Noun_mkN481-490.gfpart",
    "10_Noun_mkN491-500.gfpart",
    "10_Noun_mkN501-510.gfpart",
    "10_Noun_mkN511-520.gfpart",
    "10_Noun_mkN521-530.gfpart",
    "10_Noun_mkN531-540.gfpart",
    "10_Noun_mkN541-550.gfpart",
    "10_Noun_mkN551-560.gfpart",
    "10_Noun_mkN561-570.gfpart",
    "20_Adj_mkA001-010.gfpart",
    "20_Adj_mkA011-020.gfpart",
    "20_Adj_mkA021-030.gfpart",
    "20_Adj_mkA031-040.gfpart",
    "30_Verb_mkV001-010.gfpart",
    "30_Verb_mkV011-020.gfpart",
    "30_Verb_mkV021-030.gfpart",
    "30_Verb_mkV031-040.gfpart",
    "30_Verb_mkV041-050.gfpart",
    "30_Verb_mkV051-060.gfpart",
    "30_Verb_mkV061-070.gfpart",
    "30_Verb_mkV071-080.gfpart",
    "30_Verb_mkV081-090.gfpart",
    "30_Verb_mkV091-100.gfpart",
    "30_Verb_mkV101-110.gfpart",
    "30_Verb_mkV111-120.gfpart",
    "30_Verb_mkV121-130.gfpart",
    "30_Verb_mkV131-140.gfpart"
  ],
  "section_count": 734,
  "preamble_present": false
}
